davis_stats/__init__.py
davis_stats/data/__init__.py
davis_stats/data/ceo_comp.xlsx
davis_stats/data/just_games.xlsx
davis_stats/data/nba.xlsx
davis_stats/data/netflix_content.xlsx
davis_stats/data/olympic_medals.xlsx
davis_stats/data/restaurants.xlsx
davis_stats/data/world_cup_goals.xlsx
davis_stats/stats/__init__.py
davis_stats/stats/reg.py
davis_stats/visualization/__init__.py
davis_stats/visualization/boxplot.py
davis_stats/visualization/histogram.py
davis_stats/visualization/scatter.py
davis_stats/visualization/trim.py
davis_stats-1.3.dist-info/METADATA
davis_stats-1.3.dist-info/WHEEL
davis_stats-1.3.dist-info/top_level.txt
davis_stats-1.3.dist-info/RECORD
