Metadata-Version: 2.4
Name: davis_stats
Version: 1.3
Summary: davis_stats is a teaching-focused repository 
Author: Justin G. Davis
Author-email: 
Keywords: statistics,data science,business analytics
Requires-Python: >=3.7
Requires-Dist: pandas>=1.0.0
Requires-Dist: openpyxl>=3.0.0
Requires-Dist: numpy>=1.20.0
Requires-Dist: matplotlib>=3.0.0
Requires-Dist: scipy>=1.6.0
Requires-Dist: seaborn>=0.12.0
Requires-Dist: statsmodels>=0.14.0
Requires-Dist: ipympl>=0.8.0
Dynamic: author
Dynamic: keywords
Dynamic: requires-dist
Dynamic: requires-python
Dynamic: summary
